tests/__init__.py
tests/activations_test.py
tests/attributes_test.py
tests/convolution_test.py
tests/general_test.py
tests/jit_test.py
tests/normalization_test.py
tests/padding_test.py
tests/pickle_test.py
tests/recurrent_test.py
tests/torchlayers_test.py
torchlayers/__init__.py
torchlayers/_name.py
torchlayers/_version.py
torchlayers/activations.py
torchlayers/convolution.py
torchlayers/normalization.py
torchlayers/pooling.py
torchlayers/regularization.py
torchlayers/upsample.py
torchlayers/_dev_utils/__init__.py
torchlayers/_dev_utils/helpers.py
torchlayers/_dev_utils/infer.py
torchlayers/_dev_utils/modules.py
torchlayers/_inferable/__init__.py
torchlayers/_inferable/custom.py
torchlayers/_inferable/torch.py
torchlayers-0.1.1.dist-info/LICENSE
torchlayers-0.1.1.dist-info/METADATA
torchlayers-0.1.1.dist-info/WHEEL
torchlayers-0.1.1.dist-info/top_level.txt
torchlayers-0.1.1.dist-info/RECORD
