Metadata-Version: 2.1
Name: torchlayers
Version: 0.1.1
Summary: Input shape inference and SOTA custom layers for PyTorch.
Home-page: https://github.com/pypa/torchlayers
Author: Szymon Maszke
Author-email: szymon.maszke@protonmail.com
License: MIT
Project-URL: Website, https://szymonmaszke.github.io/torchlayers
Project-URL: Documentation, https://szymonmaszke.github.io/torchlayers/#torchlayers
Project-URL: Issues, https://github.com/szymonmaszke/torchlayers/issues?q=is%3Aissue+is%3Aopen+sort%3Aupdated-desc
Keywords: pytorch keras input inference automatic shape layers sota custom imagenet resnet efficientnet
Platform: UNKNOWN
Classifier: Development Status :: 2 - Pre-Alpha
Classifier: Programming Language :: Python
Classifier: Programming Language :: Python :: 3
Classifier: Programming Language :: Python :: 3.7
Classifier: Programming Language :: Python :: 3.8
Classifier: License :: OSI Approved :: MIT License
Classifier: Intended Audience :: Developers
Classifier: Operating System :: OS Independent
Classifier: Topic :: Scientific/Engineering
Classifier: Topic :: Software Development :: Libraries
Classifier: Topic :: Scientific/Engineering :: Artificial Intelligence
Classifier: Topic :: Software Development :: Libraries :: Python Modules
Requires-Python: >=3.7
Requires-Dist: torch (>=1.3.0)
